vito/__init__.py
vito/sas_prefect.py
sas_prefect-0.1.4.dist-info/LICENSE.md
sas_prefect-0.1.4.dist-info/METADATA
sas_prefect-0.1.4.dist-info/WHEEL
sas_prefect-0.1.4.dist-info/RECORD
