Metadata-Version: 2.1
Name: sas-prefect
Version: 0.1.4
Summary: Prefect Extensions
Author: Roeland Maes
Author-email: roeland.maes@vito.be
Requires-Python: >=3.10,<3.14
Classifier: Programming Language :: Python :: 3
Classifier: Programming Language :: Python :: 3.10
Classifier: Programming Language :: Python :: 3.11
Classifier: Programming Language :: Python :: 3.12
Requires-Dist: prefect (>=3.4,<4.0.0)
